pi_folder_organizer/__init__.py
pi_folder_organizer/_exceptions.py
pi_folder_organizer/_version.py
pi_folder_organizer/pi_folder_organizer.py
pi_folder_organizer/version.py
pi_folder_organizer-2.2.2.dist-info/LICENSE
pi_folder_organizer-2.2.2.dist-info/METADATA
pi_folder_organizer-2.2.2.dist-info/WHEEL
pi_folder_organizer-2.2.2.dist-info/top_level.txt
pi_folder_organizer-2.2.2.dist-info/RECORD
