Metadata-Version: 2.1
Name: pi-folder-organizer
Version: 2.2.2
Summary: A Python package for cleaning up cluttered files and organizing them into respective folders.
Author: Qadeer Ahmad
Author-email: mrqdeer1231122@gmail.com
Keywords: python,file organization,file cleanup,cluttered files,folder management,data organization,file management,data cleanup,Python package,developer tools,data processing,file sorting,data structuring,automated file organization,Python library,data management,data handling,file optimization,data optimization
Classifier: Development Status :: 1 - Planning
Classifier: Intended Audience :: Developers
Classifier: Programming Language :: Python :: 3
Classifier: Operating System :: Unix
Classifier: Operating System :: MacOS :: MacOS X
Classifier: Operating System :: Microsoft :: Windows
License-File: LICENSE
